buttons/__about__.py
buttons/__init__.py
buttons/apps.py
buttons/conf.py
buttons/models.py
buttons/locale/fr/LC_MESSAGES/django.mo
buttons/locale/fr/LC_MESSAGES/django.po
buttons/static/buttons/css/main.css
buttons/static/buttons/css/main.less
buttons/static/buttons/css/main.map
buttons/static/buttons/js/main.js
buttons/templates/buttons/fontawesome-4/button.html
buttons/templates/buttons/fontawesome-4/single-button.html
buttons/templates/buttons/fontawesome-4/switch-button.html
buttons/templates/buttons/fontawesome-5/button.html
buttons/templates/buttons/fontawesome-5/single-button.html
buttons/templates/buttons/fontawesome-5/switch-button.html
buttons/templates/buttons/fontawesome-6/button.html
buttons/templates/buttons/fontawesome-6/single-button.html
buttons/templates/buttons/fontawesome-6/switch-button.html
buttons/templatetags/__init__.py
buttons/templatetags/buttons_tags.py
buttons/templatetags/querystring_tags.py
django_buttons-1.0.4.dist-info/METADATA
django_buttons-1.0.4.dist-info/WHEEL
django_buttons-1.0.4.dist-info/licenses/LICENSE
django_buttons-1.0.4.dist-info/RECORD
