Metadata-Version: 2.4
Name: django-buttons
Version: 1.0.4
Summary: An application providing some template-tags to add buttons on pages
Project-URL: Homepage, https://gitlab.ville.tg/fguerin/django-buttons
Project-URL: Source, https://gitlab.ville.tg/fguerin/django-buttons
Project-URL: Documentation, http://fguerin.docs.tourcoing.fr/django-buttons
Author-email: FrançoiS GUÉRIN <fguerin@ville-tourcoing.fr>
License: MIT
License-File: LICENSE
Keywords: Bootstrap,Django,FontAwesome
Classifier: Development Status :: 4 - Beta
Classifier: Environment :: Web Environment
Classifier: Framework :: Django :: 3.2
Classifier: Framework :: Django :: 4.0
Classifier: Framework :: Django :: 4.1
Classifier: Framework :: Django :: 4.2
Classifier: Intended Audience :: Developers
Classifier: License :: OSI Approved :: MIT License
Classifier: Natural Language :: English
Classifier: Natural Language :: French
Classifier: Operating System :: OS Independent
Classifier: Programming Language :: Python
Classifier: Programming Language :: Python :: 3
Classifier: Programming Language :: Python :: 3.7
Classifier: Programming Language :: Python :: 3.8
Classifier: Programming Language :: Python :: 3.9
Classifier: Topic :: Internet
Classifier: Topic :: Internet :: WWW/HTTP :: WSGI :: Application
Classifier: Topic :: Software Development :: Libraries :: Python Modules
Requires-Python: >=3.9
Requires-Dist: django-appconf
Provides-Extra: fa5
Requires-Dist: django-fontawesome-5; extra == 'fa5'
Provides-Extra: fa6
Requires-Dist: django-fontawesome-6; extra == 'fa6'
